{
    "cr03zr7k5z700081s2tg": [
        {
            "decoding": "kde",
            "d_new": "55",
            "num_errors": 0.0,
            "error_list": [
                0,
                0
            ],
            "additional_info": {
                "rel_error": 1,
                "bandwidth_linspace": [
                    0.4,
                    0.7,
                    20
                ],
                "num_points_bandwidths": 51,
                "soft_multiplicator": 0.5
            }
        },
        {
            "decoding": "hard",
            "d_new": "55",
            "num_errors": 3.0,
            "error_list": [
                3,
                3
            ],
            "noise_list": [
                0.006896603822665341,
                0.0005406361383528327,
                0.003826880615670681,
                0.005099288749981089,
                0.027520183486238536,
                0.013760091743119268,
                0.013760091743119268
            ]
        },
        {
            "decoding": "kde",
            "d_new": "51",
            "num_errors": 0.5,
            "error_list": [
                1,
                0
            ],
            "additional_info": {
                "rel_error": 1,
                "bandwidth_linspace": [
                    0.4,
                    0.7,
                    20
                ],
                "num_points_bandwidths": 51,
                "soft_multiplicator": 0.5
            }
        },
        {
            "decoding": "hard",
            "d_new": "51",
            "num_errors": 3.0,
            "error_list": [
                3,
                3
            ],
            "noise_list": [
                0.006911577260725355,
                0.0005409234547532807,
                0.0038809599549309154,
                0.004974457838399429,
                0.028082178217821784,
                0.014041089108910892,
                0.014041089108910892
            ]
        },
        {
            "decoding": "kde",
            "d_new": "47",
            "num_errors": 1.5,
            "error_list": [
                2,
                1
            ],
            "additional_info": {
                "rel_error": 1,
                "bandwidth_linspace": [
                    0.4,
                    0.7,
                    20
                ],
                "num_points_bandwidths": 51,
                "soft_multiplicator": 0.5
            }
        },
        {
            "decoding": "hard",
            "d_new": "47",
            "num_errors": 5.5,
            "error_list": [
                7,
                4
            ],
            "noise_list": [
                0.006371159362534745,
                0.0005274592468580102,
                0.003965241428248698,
                0.004887413262394241,
                0.02813870967741935,
                0.014069354838709676,
                0.014069354838709676
            ]
        },
        {
            "decoding": "kde",
            "d_new": "43",
            "num_errors": 2.5,
            "error_list": [
                4,
                1
            ],
            "additional_info": {
                "rel_error": 1,
                "bandwidth_linspace": [
                    0.4,
                    0.7,
                    20
                ],
                "num_points_bandwidths": 51,
                "soft_multiplicator": 0.5
            }
        },
        {
            "decoding": "hard",
            "d_new": "43",
            "num_errors": 8.5,
            "error_list": [
                14,
                3
            ],
            "noise_list": [
                0.006312486999766438,
                0.0005158465220810639,
                0.0037281435512542516,
                0.004909523397127423,
                0.027428235294117646,
                0.013714117647058823,
                0.013714117647058823
            ]
        },
        {
            "decoding": "kde",
            "d_new": "39",
            "num_errors": 1.5,
            "error_list": [
                2,
                1
            ],
            "additional_info": {
                "rel_error": 1,
                "bandwidth_linspace": [
                    0.4,
                    0.7,
                    20
                ],
                "num_points_bandwidths": 51,
                "soft_multiplicator": 0.5
            }
        },
        {
            "decoding": "hard",
            "d_new": "39",
            "num_errors": 12.5,
            "error_list": [
                22,
                3
            ],
            "noise_list": [
                0.006018251570670788,
                0.0005107408458767346,
                0.0037088640234821664,
                0.0049614430483264135,
                0.0284012987012987,
                0.01420064935064935,
                0.01420064935064935
            ]
        }
    ]
}